cms_lab_members/__init__.py
cms_lab_members/admin.py
cms_lab_members/cms_app.py
cms_lab_members/cms_plugins.py
cms_lab_members/cms_toolbar.py
cms_lab_members/menu.py
cms_lab_members/models.py
cms_lab_members/tests.py
cms_lab_members/views.py
cms_lab_members/static/cms_lab_members/plugins.css
cms_lab_members/templates/cms_lab_members/plugin.html
djangocms_lab_members-0.2.0.dist-info/DESCRIPTION.rst
djangocms_lab_members-0.2.0.dist-info/METADATA
djangocms_lab_members-0.2.0.dist-info/RECORD
djangocms_lab_members-0.2.0.dist-info/WHEEL
djangocms_lab_members-0.2.0.dist-info/metadata.json
djangocms_lab_members-0.2.0.dist-info/top_level.txt
